{"usage": {"text_units": 5, "text_characters": 45632, "features": 4}, "language": "fr", "keywords": [{"text": "avoir neutre", "relevance": 0.776352, "count": 1}, {"text": "avoir de besoin", "relevance": 0.648787, "count": 1}, {"text": "reposoir de Florie", "relevance": 0.616819, "count": 1}, {"text": "bouge puis", "relevance": 0.603308, "count": 1}, {"text": "dragon Florie", "relevance": 0.556331, "count": 1}, {"text": "voix d\u2019Ad\u00e8le", "relevance": 0.556187, "count": 1}, {"text": "jeune femme", "relevance": 0.554925, "count": 6}, {"text": "quelque chose", "relevance": 0.540132, "count": 5}, {"text": "premi\u00e8re fois", "relevance": 0.531851, "count": 1}, {"text": "t\u00eate de son ouvrage", "relevance": 0.530681, "count": 1}, {"text": "Saint-Damien", "relevance": 0.530639, "count": 2}, {"text": "maison de la jeune femme", "relevance": 0.526165, "count": 1}, {"text": "grande s\u0153ur", "relevance": 0.52006, "count": 2}, {"text": "Saint-Germain", "relevance": 0.519726, "count": 2}, {"text": "CONSEIL HOULEUX", "relevance": 0.517503, "count": 1}, {"text": "r\u00e9paration de ma grosse cuve", "relevance": 0.517201, "count": 1}, {"text": "paroles d\u2019Ad\u00e8le", "relevance": 0.516191, "count": 1}, {"text": "air moqueur", "relevance": 0.516074, "count": 1}, {"text": "faire", "relevance": 0.515853, "count": 1}, {"text": "yeux noisette", "relevance": 0.514849, "count": 1}, {"text": "Allez", "relevance": 0.514819, "count": 1}, {"text": "\u00e9gard d\u2019\u00c9douard G\u00e9linas", "relevance": 0.514616, "count": 1}, {"text": "s\u00e9curit\u00e9 du village", "relevance": 0.514414, "count": 1}, {"text": "compte-rendu du reposoir de ma s\u0153ur", "relevance": 0.514172, "count": 1}, {"text": "belle soir\u00e9e de juin", "relevance": 0.513561, "count": 1}, {"text": "marche de plusieurs minutes", "relevance": 0.513419, "count": 1}, {"text": "cris de Florie", "relevance": 0.513327, "count": 1}, {"text": "rien de bon", "relevance": 0.513324, "count": 3}, {"text": "longs cils", "relevance": 0.512858, "count": 1}, {"text": "Monsieur Horace", "relevance": 0.512344, "count": 1}, {"text": "id\u00e9e du cur\u00e9", "relevance": 0.511685, "count": 1}, {"text": "Marie-Camille", "relevance": 0.511624, "count": 3}, {"text": "quelques heures", "relevance": 0.511376, "count": 1}, {"text": "Jeremiah Holland", "relevance": 0.511311, "count": 1}, {"text": "cadet de la famille", "relevance": 0.511304, "count": 1}, {"text": "ann\u00e9e derni\u00e8re", "relevance": 0.511113, "count": 1}, {"text": "trouble de James", "relevance": 0.510442, "count": 1}, {"text": "reproches fr\u00e9quents de Florie", "relevance": 0.510423, "count": 1}, {"text": "travaux de couture", "relevance": 0.510229, "count": 1}, {"text": "\u00c9douard", "relevance": 0.50965, "count": 34}, {"text": "nouveau fromage", "relevance": 0.5092, "count": 1}, {"text": "jeune homme", "relevance": 0.508936, "count": 5}, {"text": "39Tout", "relevance": 0.508506, "count": 1}, {"text": "vieux Saint-Germain", "relevance": 0.508154, "count": 1}, {"text": "vrai Canadien", "relevance": 0.508145, "count": 1}, {"text": "robe rouge", "relevance": 0.507646, "count": 1}, {"text": "Merci de ta g\u00e9n\u00e9rosit\u00e9", "relevance": 0.507596, "count": 1}, {"text": "quelque chose de petit", "relevance": 0.507181, "count": 1}, {"text": "Henry Stromph", "relevance": 0.507175, "count": 1}, {"text": "fougueuse Ad\u00e8le G\u00e9linas", "relevance": 0.507069, "count": 1}], "entities": [{"type": "Person", "text": "Florie", "relevance": 0.954649, "count": 40}, {"type": "Person", "text": "\u00c9douard", "relevance": 0.90783, "count": 33}, {"type": "Person", "text": "Ad\u00e8le", "relevance": 0.550068, "count": 27}, {"type": "Person", "text": "James", "relevance": 0.529215, "count": 17}, {"type": "Person", "text": "Constantin", "relevance": 0.385743, "count": 6}, {"type": "Number", "text": "deux", "relevance": 0.353969, "count": 29}, {"type": "Person", "text": "Anasthase", "relevance": 0.326859, "count": 5}, {"type": "Number", "text": "un", "relevance": 0.275683, "count": 59}, {"type": "JobTitle", "text": "maire", "relevance": 0.2627, "count": 9}, {"type": "Person", "text": "ma\u00eetre-beurrier", "relevance": 0.246017, "count": 3}, {"type": "Person", "text": "Laurent", "relevance": 0.213181, "count": 14}, {"type": "Person", "text": "Jeremiah", "relevance": 0.211947, "count": 8}, {"type": "Person", "text": "G\u00e9linas", "relevance": 0.207596, "count": 5}, {"type": "JobTitle", "text": "conseillers", "relevance": 0.200557, "count": 5}, {"type": "Person", "text": "Alcide Constantin", "relevance": 0.19986, "count": 3}, {"type": "Person", "text": "Alcide", "relevance": 0.18978, "count": 3}, {"type": "Person", "text": "\n\u00c9douar", "relevance": 0.182696, "count": 2}, {"type": "Duration", "text": "plusieurs minutes", "relevance": 0.148311, "count": 2}, {"type": "JobTitle", "text": "fermier", "relevance": 0.142728, "count": 2}, {"type": "Duration", "text": "quelques secondes", "relevance": 0.142622, "count": 3}, {"type": "Person", "text": "Ludovic", "relevance": 0.141945, "count": 6}, {"type": "Location", "text": "Labelle", "relevance": 0.13862, "count": 2}, {"type": "Person", "text": "Rosaire Barnab\u00e9", "relevance": 0.135821, "count": 2}, {"type": "Location", "text": "Saint-Germain", "relevance": 0.133343, "count": 2}, {"type": "Number", "text": "trois", "relevance": 0.11135, "count": 6}, {"type": "Person", "text": "Louisette", "relevance": 0.111272, "count": 3}, {"type": "Ordinal", "text": "premi\u00e8re", "relevance": 0.11062, "count": 5}, {"type": "JobTitle", "text": "conseiller", "relevance": 0.101701, "count": 3}, {"type": "JobTitle", "text": "fermiers", "relevance": 0.098613, "count": 1}, {"type": "Time", "text": "t\u00f4t le matin", "relevance": 0.09848, "count": 1}, {"type": "Number", "text": "trente-cinq", "relevance": 0.098355, "count": 1}, {"type": "Duration", "text": "depuis des ann\u00e9es", "relevance": 0.098239, "count": 1}, {"type": "Duration", "text": "six ans", "relevance": 0.097347, "count": 1}, {"type": "Date", "text": "cette semaine", "relevance": 0.096625, "count": 1}, {"type": "Duration", "text": "deux minutes", "relevance": 0.09646, "count": 1}, {"type": "Date", "text": "d\u00e9but du mois de juillet", "relevance": 0.095155, "count": 1}, {"type": "Person", "text": "beurrier", "relevance": 0.090996, "count": 1}, {"type": "Person", "text": "agrippa", "relevance": 0.090822, "count": 1}, {"type": "Duration", "text": "quelques\nsecondes", "relevance": 0.089353, "count": 1}, {"type": "Time", "text": "tard ce soir", "relevance": 0.089045, "count": 1}, {"type": "Duration", "text": "plusieurs jours", "relevance": 0.088959, "count": 1}, {"type": "Person", "text": " Jame", "relevance": 0.088063, "count": 1}, {"type": "Number", "text": "dois", "relevance": 0.084144, "count": 3}, {"type": "Organization", "text": "this insane", "relevance": 0.08264, "count": 1}, {"type": "Date", "text": "15 juin", "relevance": 0.080854, "count": 1}, {"type": "Person", "text": "Alcide\nConstantin", "relevance": 0.080737, "count": 1}, {"type": "JobTitle", "text": "commer\u00e7ant", "relevance": 0.080476, "count": 1}, {"type": "Person", "text": "Henry Stromph", "relevance": 0.080057, "count": 1}, {"type": "Date", "text": "juin", "relevance": 0.078902, "count": 3}, {"type": "Ordinal", "text": "derni\u00e8res", "relevance": 0.078785, "count": 3}], "concepts": [{"text": "Qu\u00e9bec", "relevance": 0.988747, "dbpedia_resource": "http://fr.dbpedia.org/resource/Qu\u00e9bec"}, {"text": "Fille", "relevance": 0.984106, "dbpedia_resource": "http://fr.dbpedia.org/resource/Fille"}, {"text": "Parole", "relevance": 0.97488, "dbpedia_resource": "http://fr.dbpedia.org/resource/Parole"}, {"text": "Fratrie", "relevance": 0.95876, "dbpedia_resource": "http://fr.dbpedia.org/resource/Fratrie"}, {"text": "Sommeil", "relevance": 0.9316, "dbpedia_resource": "http://fr.dbpedia.org/resource/Sommeil"}, {"text": "Sourire", "relevance": 0.914191, "dbpedia_resource": "http://fr.dbpedia.org/resource/Sourire"}, {"text": "Commerce", "relevance": 0.877658, "dbpedia_resource": "http://fr.dbpedia.org/resource/Commerce"}, {"text": "Silence", "relevance": 0.870355, "dbpedia_resource": "http://fr.dbpedia.org/resource/Silence"}], "categories": [{"score": 0.722004, "label": "/art and entertainment/shows and events"}, {"score": 0.688223, "label": "/business and industrial/business operations/business plans"}, {"score": 0.631637, "label": "/family and parenting/babies and toddlers/baby clothes"}]}