{"usage": {"text_units": 3, "text_characters": 25317, "features": 4}, "language": "fr", "keywords": [{"text": "jambes de T\u00e9o", "relevance": 0.599162, "count": 1}, {"text": "femmes sales", "relevance": 0.545371, "count": 1}, {"text": "jeunes \u00e9tudiants", "relevance": 0.543253, "count": 1}, {"text": "fa\u00e7on de le faire", "relevance": 0.539948, "count": 1}, {"text": "T\u00e9o", "relevance": 0.537343, "count": 41}, {"text": "coin des rues", "relevance": 0.53096, "count": 1}, {"text": "messe du dimanche", "relevance": 0.528076, "count": 3}, {"text": "seul Dieu", "relevance": 0.525777, "count": 1}, {"text": "autre jeune", "relevance": 0.524546, "count": 1}, {"text": "horloge du tableau de bord", "relevance": 0.52194, "count": 1}, {"text": "quelque chose de surr\u00e9aliste", "relevance": 0.521661, "count": 1}, {"text": "jeunes femmes", "relevance": 0.52134, "count": 4}, {"text": "femme affreuse", "relevance": 0.520893, "count": 1}, {"text": "dame du dix-neuvi\u00e8me si\u00e8cle", "relevance": 0.520844, "count": 1}, {"text": "Clarice", "relevance": 0.520432, "count": 42}, {"text": "petits vieux", "relevance": 0.520157, "count": 1}, {"text": "devoir d\u2019un catholique", "relevance": 0.519193, "count": 1}, {"text": "pauvre ami", "relevance": 0.519036, "count": 1}, {"text": "premier probl\u00e8me", "relevance": 0.518915, "count": 1}, {"text": "faire quelques", "relevance": 0.517978, "count": 1}, {"text": "nouvel ordre", "relevance": 0.516335, "count": 1}, {"text": "jeunes gens", "relevance": 0.514275, "count": 1}, {"text": "mademoiselle Clarice", "relevance": 0.514054, "count": 2}, {"text": "Opel Corsa rouge", "relevance": 0.513992, "count": 1}, {"text": "m\u00e8re d\u2019un baiser nerveux", "relevance": 0.513926, "count": 1}, {"text": "histoire de l\u2019art", "relevance": 0.513579, "count": 1}, {"text": "femme de l\u2019accueil", "relevance": 0.512765, "count": 1}, {"text": "premi\u00e8re r\u00e9action de T\u00e9o", "relevance": 0.512554, "count": 1}, {"text": "rue \u00e9troite", "relevance": 0.512119, "count": 1}, {"text": "baryton-basse", "relevance": 0.511952, "count": 1}, {"text": "longue de plusieurs m\u00e8tres", "relevance": 0.511405, "count": 1}, {"text": "cr\u00e9dulit\u00e9 de certains fid\u00e8les", "relevance": 0.511404, "count": 1}, {"text": "multitude de visages", "relevance": 0.511285, "count": 1}, {"text": "lieu de l\u2019euphorie", "relevance": 0.511284, "count": 1}, {"text": "fin de la messe", "relevance": 0.511246, "count": 1}, {"text": "question provocante", "relevance": 0.511229, "count": 1}, {"text": "cheveux exotiques", "relevance": 0.510913, "count": 1}, {"text": "examen d\u2019entr\u00e9e", "relevance": 0.510497, "count": 1}, {"text": "seul corps", "relevance": 0.510411, "count": 1}, {"text": "Orchestre symphonique br\u00e9silien", "relevance": 0.510279, "count": 1}, {"text": "voix haute", "relevance": 0.51011, "count": 1}, {"text": "parlant seule", "relevance": 0.509991, "count": 1}, {"text": "coin de rue d\u00e9sert", "relevance": 0.509898, "count": 1}, {"text": "genre de femme", "relevance": 0.509327, "count": 1}, {"text": "Seigneur J\u00e9sus", "relevance": 0.509233, "count": 1}, {"text": "si\u00e8ge du passager de la Vectra", "relevance": 0.508991, "count": 1}, {"text": "t\u00eate des id\u00e9es absurdes", "relevance": 0.508941, "count": 1}, {"text": "Fin de cinqui\u00e8me ann\u00e9e", "relevance": 0.508764, "count": 1}, {"text": "souci de la pluie", "relevance": 0.508695, "count": 1}, {"text": "haut de la liste", "relevance": 0.50867, "count": 1}], "entities": [{"type": "Person", "text": "Clarice", "relevance": 0.959655, "count": 47}, {"type": "Person", "text": "T\u00e9o", "relevance": 0.845021, "count": 39}, {"type": "Person", "text": "Patr\u00edcia", "relevance": 0.19122, "count": 5}, {"type": "Number", "text": "un", "relevance": 0.1522, "count": 44}, {"type": "Person", "text": "Seigneur", "relevance": 0.129855, "count": 5}, {"type": "Time", "text": "la veille au soir", "relevance": 0.126493, "count": 2}, {"type": "Person", "text": "Dieu le P\u00e8re", "relevance": 0.120139, "count": 2}, {"type": "Location", "text": "Copacabana", "relevance": 0.112407, "count": 2}, {"type": "Ordinal", "text": "cinqui\u00e8me", "relevance": 0.108381, "count": 4}, {"type": "Date", "text": "quelle ann\u00e9e", "relevance": 0.100766, "count": 2}, {"type": "Organization", "text": "UERJ", "relevance": 0.098725, "count": 2}, {"type": "Person", "text": "Gertrudes", "relevance": 0.097678, "count": 2}, {"type": "Person", "text": "Sans\u00e3o", "relevance": 0.09704, "count": 2}, {"type": "Person", "text": "Clarice Manh\u00e3es", "relevance": 0.089807, "count": 2}, {"type": "Person", "text": "Dieu", "relevance": 0.073658, "count": 4}, {"type": "Number", "text": "deux", "relevance": 0.073531, "count": 9}, {"type": "JobTitle", "text": "infirmier", "relevance": 0.066015, "count": 1}, {"type": "Person", "text": "\nT\u00e9", "relevance": 0.065326, "count": 1}, {"type": "Date", "text": " dimanch", "relevance": 0.065245, "count": 1}, {"type": "JobTitle", "text": "surr\u00e9aliste", "relevance": 0.064512, "count": 1}, {"type": "Person", "text": "T\u00e9o. Enfant", "relevance": 0.063551, "count": 1}, {"type": "Duration", "text": "soixante minutes", "relevance": 0.062025, "count": 1}, {"type": "Person", "text": "Seigneur Dieu", "relevance": 0.061978, "count": 1}, {"type": "Person", "text": "J\u00e9sus-Christ", "relevance": 0.061772, "count": 1}, {"type": "Person", "text": "Vierge Marie", "relevance": 0.061153, "count": 1}, {"type": "Person", "text": "bienheureuse M\u00e8re de Dieu", "relevance": 0.06109, "count": 1}, {"type": "JobTitle", "text": "ap\u00f4tres", "relevance": 0.061018, "count": 1}, {"type": "Organization", "text": "Esprit saint", "relevance": 0.060831, "count": 1}, {"type": "Date", "text": "dimanche-l\u00e0", "relevance": 0.059941, "count": 1}, {"type": "Time", "text": "\u00c0 la fin de la messe", "relevance": 0.057363, "count": 1}, {"type": "Person", "text": "Christ", "relevance": 0.057132, "count": 2}, {"type": "GeographicFeature", "text": "terre", "relevance": 0.05696, "count": 3}, {"type": "Person", "text": "Patr\u00edcia tomba", "relevance": 0.05668, "count": 1}, {"type": "Duration", "text": "plusieurs semaines", "relevance": 0.056517, "count": 1}, {"type": "Location", "text": "S\u00e3o Paulo", "relevance": 0.054229, "count": 1}, {"type": "JobTitle", "text": "chauffeur", "relevance": 0.054176, "count": 3}, {"type": "Person", "text": "mademoiselle Clarice", "relevance": 0.054043, "count": 1}, {"type": "Organization", "text": "Institut br\u00e9silien de g\u00e9ographie et de\nstatistiques", "relevance": 0.053922, "count": 1}, {"type": "Person", "text": "Manh\u00e3es", "relevance": 0.053448, "count": 1}, {"type": "Measure", "text": " Vingt-quatre an", "relevance": 0.053252, "count": 1}, {"type": "Duration", "text": "deux ans", "relevance": 0.053137, "count": 1}, {"type": "JobTitle", "text": "automobiliste", "relevance": 0.052614, "count": 1}, {"type": "Location", "text": "Rio de Janeiro", "relevance": 0.051536, "count": 1}, {"type": "Time", "text": "Ce soir", "relevance": 0.051478, "count": 2}, {"type": "Person", "text": "UERJ", "relevance": 0.051365, "count": 1}, {"type": "Duration", "text": "\u00c0 quelle heure", "relevance": 0.051327, "count": 1}, {"type": "Time", "text": "sept heures du matin", "relevance": 0.051196, "count": 1}, {"type": "Time", "text": "dimanche apr\u00e8s-midi", "relevance": 0.049414, "count": 1}, {"type": "Time", "text": "Le\nsoir", "relevance": 0.049232, "count": 1}, {"type": "Organization", "text": "facult\u00e9 d\u2019histoire de l\u2019art", "relevance": 0.048711, "count": 1}], "concepts": [{"text": "Messe", "relevance": 0.985893, "dbpedia_resource": "http://fr.dbpedia.org/resource/Messe"}, {"text": "Fille", "relevance": 0.973037, "dbpedia_resource": "http://fr.dbpedia.org/resource/Fille"}, {"text": "T\u00e9l\u00e9phone", "relevance": 0.966866, "dbpedia_resource": "http://fr.dbpedia.org/resource/T\u00e9l\u00e9phone"}, {"text": "Cin\u00e9ma", "relevance": 0.964752, "dbpedia_resource": "http://fr.dbpedia.org/resource/Cin\u00e9ma"}, {"text": "Sourire", "relevance": 0.913751, "dbpedia_resource": "http://fr.dbpedia.org/resource/Sourire"}, {"text": "Enfant", "relevance": 0.896651, "dbpedia_resource": "http://fr.dbpedia.org/resource/Enfant"}, {"text": "Parole", "relevance": 0.883627, "dbpedia_resource": "http://fr.dbpedia.org/resource/Parole"}, {"text": "Charit\u00e9", "relevance": 0.854632, "dbpedia_resource": "http://fr.dbpedia.org/resource/Charit\u00e9"}], "categories": [{"score": 0.873685, "label": "/society/social institution/divorce"}, {"score": 0.781647, "label": "/family and parenting/children"}, {"score": 0.646971, "label": "/family and parenting/babies and toddlers/baby clothes"}]}