{"entities": [{"type": "PERSON", "mention": "Louis Cardinal", "normalized": "Louis Cardinal", "count": 41, "mentionOffsets": [{"startOffset": 4159, "endOffset": 4173}, {"startOffset": 5173, "endOffset": 5178}, {"startOffset": 5602, "endOffset": 5607}, {"startOffset": 6230, "endOffset": 6235}, {"startOffset": 6833, "endOffset": 6838}, {"startOffset": 6985, "endOffset": 6990}, {"startOffset": 7569, "endOffset": 7574}, {"startOffset": 7985, "endOffset": 7990}, {"startOffset": 8251, "endOffset": 8256}, {"startOffset": 8312, "endOffset": 8317}, {"startOffset": 8815, "endOffset": 8820}, {"startOffset": 9998, "endOffset": 10003}, {"startOffset": 10220, "endOffset": 10225}, {"startOffset": 10394, "endOffset": 10399}, {"startOffset": 10733, "endOffset": 10738}, {"startOffset": 23033, "endOffset": 23038}, {"startOffset": 24103, "endOffset": 24108}, {"startOffset": 24326, "endOffset": 24331}, {"startOffset": 25122, "endOffset": 25127}, {"startOffset": 26142, "endOffset": 26147}, {"startOffset": 26362, "endOffset": 26367}, {"startOffset": 26920, "endOffset": 26925}, {"startOffset": 26965, "endOffset": 26970}, {"startOffset": 28798, "endOffset": 28803}, {"startOffset": 29370, "endOffset": 29375}, {"startOffset": 29835, "endOffset": 29840}, {"startOffset": 30687, "endOffset": 30692}, {"startOffset": 30997, "endOffset": 31002}, {"startOffset": 31150, "endOffset": 31155}, {"startOffset": 31855, "endOffset": 31860}, {"startOffset": 32115, "endOffset": 32120}, {"startOffset": 32232, "endOffset": 32237}, {"startOffset": 32673, "endOffset": 32678}, {"startOffset": 32869, "endOffset": 32874}, {"startOffset": 33256, "endOffset": 33261}, {"startOffset": 34221, "endOffset": 34226}, {"startOffset": 34729, "endOffset": 34734}, {"startOffset": 35190, "endOffset": 35195}, {"startOffset": 38394, "endOffset": 38399}, {"startOffset": 38837, "endOffset": 38842}, {"startOffset": 39021, "endOffset": 39035}], "entityId": "T25", "confidence": 0.59620392}, {"type": "PERSON", "mention": "Benjamin Landry", "normalized": "Benjamin Landry", "count": 25, "mentionOffsets": [{"startOffset": 50, "endOffset": 65}, {"startOffset": 2053, "endOffset": 2061}, {"startOffset": 2815, "endOffset": 2823}, {"startOffset": 3371, "endOffset": 3379}, {"startOffset": 4370, "endOffset": 4378}, {"startOffset": 4690, "endOffset": 4698}, {"startOffset": 5430, "endOffset": 5438}, {"startOffset": 6077, "endOffset": 6092}, {"startOffset": 6154, "endOffset": 6162}, {"startOffset": 6798, "endOffset": 6806}, {"startOffset": 7643, "endOffset": 7651}, {"startOffset": 8211, "endOffset": 8219}, {"startOffset": 8580, "endOffset": 8588}, {"startOffset": 8880, "endOffset": 8888}, {"startOffset": 9148, "endOffset": 9156}, {"startOffset": 9401, "endOffset": 9409}, {"startOffset": 9627, "endOffset": 9635}, {"startOffset": 10303, "endOffset": 10311}, {"startOffset": 10694, "endOffset": 10702}, {"startOffset": 34645, "endOffset": 34660}, {"startOffset": 35725, "endOffset": 35733}, {"startOffset": 36063, "endOffset": 36071}, {"startOffset": 38454, "endOffset": 38462}, {"startOffset": 38936, "endOffset": 38951}, {"startOffset": 39055, "endOffset": 39063}], "entityId": "T2", "confidence": 0.92193192}, {"type": "PERSON", "mention": "Roxane Archambault", "normalized": "Roxane Archambault", "count": 23, "mentionOffsets": [{"startOffset": 11223, "endOffset": 11229}, {"startOffset": 12339, "endOffset": 12345}, {"startOffset": 12825, "endOffset": 12831}, {"startOffset": 12949, "endOffset": 12955}, {"startOffset": 13059, "endOffset": 13065}, {"startOffset": 13620, "endOffset": 13626}, {"startOffset": 13803, "endOffset": 13809}, {"startOffset": 13876, "endOffset": 13882}, {"startOffset": 13987, "endOffset": 13993}, {"startOffset": 14688, "endOffset": 14694}, {"startOffset": 15356, "endOffset": 15362}, {"startOffset": 16712, "endOffset": 16718}, {"startOffset": 18232, "endOffset": 18238}, {"startOffset": 19108, "endOffset": 19114}, {"startOffset": 19271, "endOffset": 19277}, {"startOffset": 19453, "endOffset": 19459}, {"startOffset": 19880, "endOffset": 19886}, {"startOffset": 20410, "endOffset": 20416}, {"startOffset": 20727, "endOffset": 20733}, {"startOffset": 20793, "endOffset": 20804}, {"startOffset": 20981, "endOffset": 20987}, {"startOffset": 21939, "endOffset": 21945}, {"startOffset": 23718, "endOffset": 23736}], "entityId": "T188", "confidence": 0.92446029}, {"type": "PERSON", "mention": "Francis", "normalized": "Francis", "count": 18, "mentionOffsets": [{"startOffset": 8981, "endOffset": 8988}, {"startOffset": 10433, "endOffset": 10440}, {"startOffset": 23090, "endOffset": 23097}, {"startOffset": 23461, "endOffset": 23468}, {"startOffset": 24132, "endOffset": 24139}, {"startOffset": 24285, "endOffset": 24292}, {"startOffset": 24485, "endOffset": 24492}, {"startOffset": 24739, "endOffset": 24746}, {"startOffset": 25260, "endOffset": 25267}, {"startOffset": 25411, "endOffset": 25418}, {"startOffset": 26165, "endOffset": 26172}, {"startOffset": 26682, "endOffset": 26689}, {"startOffset": 27503, "endOffset": 27510}, {"startOffset": 29361, "endOffset": 29368}, {"startOffset": 29620, "endOffset": 29627}, {"startOffset": 29894, "endOffset": 29901}, {"startOffset": 30708, "endOffset": 30715}, {"startOffset": 33031, "endOffset": 33038}], "entityId": "T61", "confidence": 0.91164058}, {"type": "PERSON", "mention": "Herv\u00e9 Dupuis", "normalized": "Herv\u00e9 Dupuis", "count": 15, "mentionOffsets": [{"startOffset": 8096, "endOffset": 8108}, {"startOffset": 8522, "endOffset": 8527}, {"startOffset": 8954, "endOffset": 8959}, {"startOffset": 10076, "endOffset": 10081}, {"startOffset": 10424, "endOffset": 10429}, {"startOffset": 23110, "endOffset": 23115}, {"startOffset": 25460, "endOffset": 25465}, {"startOffset": 25535, "endOffset": 25540}, {"startOffset": 25745, "endOffset": 25750}, {"startOffset": 26026, "endOffset": 26031}, {"startOffset": 26075, "endOffset": 26080}, {"startOffset": 27665, "endOffset": 27670}, {"startOffset": 29255, "endOffset": 29260}, {"startOffset": 30251, "endOffset": 30256}, {"startOffset": 32785, "endOffset": 32790}], "entityId": "T46", "confidence": 0.91399485}, {"type": "PERSON", "mention": "Aline Dagenais", "normalized": "Aline Dagenais", "count": 14, "mentionOffsets": [{"startOffset": 11318, "endOffset": 11332}, {"startOffset": 11485, "endOffset": 11493}, {"startOffset": 12391, "endOffset": 12399}, {"startOffset": 13979, "endOffset": 13984}, {"startOffset": 14208, "endOffset": 14216}, {"startOffset": 14735, "endOffset": 14743}, {"startOffset": 14871, "endOffset": 14876}, {"startOffset": 15129, "endOffset": 15134}, {"startOffset": 16874, "endOffset": 16879}, {"startOffset": 18525, "endOffset": 18539}, {"startOffset": 18715, "endOffset": 18723}, {"startOffset": 19708, "endOffset": 19713}, {"startOffset": 19870, "endOffset": 19878}, {"startOffset": 20670, "endOffset": 20675}], "entityId": "T82", "confidence": 0.90350842}, {"type": "PERSON", "mention": "H\u00e9l\u00e8ne Pellerin", "normalized": "H\u00e9l\u00e8ne Pellerin", "count": 11, "mentionOffsets": [{"startOffset": 11338, "endOffset": 11353}, {"startOffset": 12166, "endOffset": 12181}, {"startOffset": 12873, "endOffset": 12881}, {"startOffset": 13002, "endOffset": 13008}, {"startOffset": 13601, "endOffset": 13607}, {"startOffset": 14329, "endOffset": 14335}, {"startOffset": 15696, "endOffset": 15702}, {"startOffset": 16456, "endOffset": 16462}, {"startOffset": 17860, "endOffset": 17875}, {"startOffset": 18759, "endOffset": 18765}, {"startOffset": 19895, "endOffset": 19901}], "entityId": "T83", "confidence": 0.77838659}, {"type": "LOCATION", "mention": "Chambly", "normalized": "Chambly", "count": 8, "mentionOffsets": [{"startOffset": 11, "endOffset": 18}, {"startOffset": 316, "endOffset": 323}, {"startOffset": 1816, "endOffset": 1823}, {"startOffset": 19069, "endOffset": 19076}, {"startOffset": 21986, "endOffset": 21993}, {"startOffset": 28951, "endOffset": 28958}, {"startOffset": 30822, "endOffset": 30829}, {"startOffset": 33218, "endOffset": 33225}], "entityId": "T0", "confidence": 0.90240949}, {"type": "PERSON", "mention": "Maryse Aubert", "normalized": "Maryse Aubert", "count": 7, "mentionOffsets": [{"startOffset": 23230, "endOffset": 23243}, {"startOffset": 23786, "endOffset": 23792}, {"startOffset": 24437, "endOffset": 24443}, {"startOffset": 24750, "endOffset": 24756}, {"startOffset": 25887, "endOffset": 25893}, {"startOffset": 26064, "endOffset": 26070}, {"startOffset": 33081, "endOffset": 33087}], "entityId": "T186", "confidence": 0.91317242}, {"type": "PERSON", "mention": "Claire", "normalized": "Claire", "count": 7, "mentionOffsets": [{"startOffset": 33265, "endOffset": 33271}, {"startOffset": 34021, "endOffset": 34027}, {"startOffset": 34555, "endOffset": 34561}, {"startOffset": 34971, "endOffset": 34977}, {"startOffset": 35917, "endOffset": 35923}, {"startOffset": 37547, "endOffset": 37553}, {"startOffset": 38352, "endOffset": 38358}], "entityId": "T260", "confidence": 0.42792273}, {"type": "LOCATION", "mention": "Montr\u00e9al", "normalized": "Montr\u00e9al", "count": 5, "mentionOffsets": [{"startOffset": 1602, "endOffset": 1610}, {"startOffset": 2464, "endOffset": 2472}, {"startOffset": 11184, "endOffset": 11192}, {"startOffset": 28002, "endOffset": 28010}, {"startOffset": 29976, "endOffset": 29984}], "entityId": "T7", "confidence": 0.94652265}, {"type": "PERSON", "mention": "Isabelle Laforte", "normalized": "Isabelle Laforte", "count": 5, "mentionOffsets": [{"startOffset": 30623, "endOffset": 30639}, {"startOffset": 30850, "endOffset": 30858}, {"startOffset": 31211, "endOffset": 31219}, {"startOffset": 31437, "endOffset": 31445}, {"startOffset": 31956, "endOffset": 31964}], "entityId": "T236", "confidence": 0.90756828}, {"type": "ORGANIZATION", "mention": "Ovide", "normalized": "Ovide", "count": 4, "mentionOffsets": [{"startOffset": 12210, "endOffset": 12215}, {"startOffset": 20155, "endOffset": 20160}, {"startOffset": 20551, "endOffset": 20556}, {"startOffset": 20955, "endOffset": 20960}], "entityId": "T90", "confidence": 0.26734138}, {"type": "ORGANIZATION", "mention": "Parti bureaucrate", "normalized": "Parti bureaucrate", "count": 3, "mentionOffsets": [{"startOffset": 972, "endOffset": 989}, {"startOffset": 3797, "endOffset": 3814}, {"startOffset": 6955, "endOffset": 6972}], "entityId": "T5", "confidence": 0.3677572}, {"type": "ORGANIZATION", "mention": "Parti patriote", "normalized": "Parti patriote", "count": 3, "mentionOffsets": [{"startOffset": 6030, "endOffset": 6044}, {"startOffset": 7689, "endOffset": 7703}, {"startOffset": 36309, "endOffset": 36323}], "entityId": "T32", "confidence": 0.55204213}, {"type": "PERSON", "mention": "Gosford", "normalized": "Gosford", "count": 3, "mentionOffsets": [{"startOffset": 9352, "endOffset": 9359}, {"startOffset": 16501, "endOffset": 16508}, {"startOffset": 36551, "endOffset": 36558}], "entityId": "T64", "confidence": 0.72252977}, {"type": "PERSON", "mention": "Matthew", "normalized": "Matthew", "count": 3, "mentionOffsets": [{"startOffset": 20002, "endOffset": 20009}, {"startOffset": 20326, "endOffset": 20333}, {"startOffset": 21561, "endOffset": 21568}], "entityId": "T158", "confidence": 0.2171284}, {"type": "LOCATION", "mention": "Canada", "normalized": "Canada", "count": 2, "mentionOffsets": [{"startOffset": 1754, "endOffset": 1760}, {"startOffset": 21306, "endOffset": 21312}], "entityId": "T9", "confidence": 0.65598536}, {"type": "PERSON", "mention": "Pis Papineau", "normalized": "Pis Papineau", "count": 2, "mentionOffsets": [{"startOffset": 3098, "endOffset": 3110}, {"startOffset": 18447, "endOffset": 18455}], "entityId": "T22", "confidence": 0.27667773}, {"type": "ORGANIZATION", "mention": "Assembl\u00e9e", "normalized": "Assembl\u00e9e", "count": 2, "mentionOffsets": [{"startOffset": 5748, "endOffset": 5757}, {"startOffset": 7361, "endOffset": 7370}], "entityId": "T31", "confidence": 0.8156116}, {"type": "PERSON", "mention": "Dieu", "normalized": "Dieu", "count": 2, "mentionOffsets": [{"startOffset": 8163, "endOffset": 8167}, {"startOffset": 39132, "endOffset": 39136}], "entityId": "T47", "confidence": 0.42866576}, {"type": "ORGANIZATION", "mention": "Toi", "normalized": "Toi", "count": 2, "mentionOffsets": [{"startOffset": 9180, "endOffset": 9183}, {"startOffset": 9548, "endOffset": 9551}], "entityId": "T63", "confidence": 0.72894681}, {"type": "TEMPORAL:TIME", "mention": "Un jour", "normalized": "Un jour", "count": 2, "mentionOffsets": [{"startOffset": 10876, "endOffset": 10883}, {"startOffset": 34918, "endOffset": 34925}], "entityId": "T78"}, {"type": "LOCATION", "mention": "Ovide Dagenais", "normalized": "Ovide Dagenais", "count": 2, "mentionOffsets": [{"startOffset": 11495, "endOffset": 11509}, {"startOffset": 20011, "endOffset": 20025}], "entityId": "T86", "confidence": 0.11554265}, {"type": "TEMPORAL:TIME", "mention": "deux semaines", "normalized": "deux semaines", "count": 2, "mentionOffsets": [{"startOffset": 12097, "endOffset": 12110}, {"startOffset": 30777, "endOffset": 30790}], "entityId": "T88"}, {"type": "TEMPORAL:DATE", "mention": "juin", "normalized": "juin", "count": 2, "mentionOffsets": [{"startOffset": 16520, "endOffset": 16524}, {"startOffset": 34463, "endOffset": 34467}], "entityId": "T123"}, {"type": "PERSON", "mention": "Albert Montreuil", "normalized": "Albert Montreuil", "count": 2, "mentionOffsets": [{"startOffset": 22253, "endOffset": 22269}, {"startOffset": 26619, "endOffset": 26635}], "entityId": "T181", "confidence": 0.58151317}, {"type": "PERSON", "mention": "Bunker", "normalized": "Bunker", "count": 2, "mentionOffsets": [{"startOffset": 29037, "endOffset": 29043}, {"startOffset": 38199, "endOffset": 38205}], "entityId": "T227", "confidence": 0.10153174}, {"type": "TEMPORAL:DATE", "mention": "vendredi, 1er septembre 1837", "normalized": "vendredi, 1er septembre 1837", "count": 1, "mentionOffsets": [{"startOffset": 20, "endOffset": 48}], "entityId": "T1"}, {"type": "TEMPORAL:DATE", "mention": "vendredi", "normalized": "vendredi", "count": 1, "mentionOffsets": [{"startOffset": 915, "endOffset": 923}], "entityId": "T4"}, {"type": "PERSON", "mention": "Louis-Joseph Papineau", "normalized": "Louis-Joseph Papineau", "count": 1, "mentionOffsets": [{"startOffset": 1183, "endOffset": 1204}], "entityId": "T6", "confidence": 0.14417922}, {"type": "LOCATION", "mention": "Lachine", "normalized": "Lachine", "count": 1, "mentionOffsets": [{"startOffset": 1693, "endOffset": 1700}], "entityId": "T8", "confidence": 0.39855611}, {"type": "LOCATION", "mention": "Angleterre", "normalized": "Angleterre", "count": 1, "mentionOffsets": [{"startOffset": 2207, "endOffset": 2217}], "entityId": "T12", "confidence": 0.46107471}, {"type": "ORGANIZATION", "mention": "parlement", "normalized": "parlement", "count": 1, "mentionOffsets": [{"startOffset": 2330, "endOffset": 2339}], "entityId": "T13", "confidence": 0.38901234}, {"type": "TITLE", "mention": "roi", "normalized": "roi", "count": 1, "mentionOffsets": [{"startOffset": 2365, "endOffset": 2368}], "entityId": "T14", "confidence": 0.47114635}, {"type": "PERSON", "mention": "Guillaume IV", "normalized": "Guillaume IV", "count": 1, "mentionOffsets": [{"startOffset": 2369, "endOffset": 2381}], "entityId": "T15", "confidence": 0.45950031}, {"type": "PERSON", "mention": "Viger", "normalized": "Viger", "count": 1, "mentionOffsets": [{"startOffset": 3046, "endOffset": 3051}], "entityId": "T18", "confidence": 0.13059223}, {"type": "PERSON", "mention": "Girouard", "normalized": "Girouard", "count": 1, "mentionOffsets": [{"startOffset": 3053, "endOffset": 3061}], "entityId": "T19", "confidence": 0.11408758}, {"type": "LOCATION", "mention": "Boucherville", "normalized": "Boucherville", "count": 1, "mentionOffsets": [{"startOffset": 3069, "endOffset": 3081}], "entityId": "T20", "confidence": 0.25862134}, {"type": "LOCATION", "mention": "Lorimier", "normalized": "Lorimier", "count": 1, "mentionOffsets": [{"startOffset": 3088, "endOffset": 3096}], "entityId": "T21", "confidence": 0.46937525}, {"type": "TITLE", "mention": "gouverneur", "normalized": "gouverneur", "count": 1, "mentionOffsets": [{"startOffset": 6937, "endOffset": 6947}], "entityId": "T38", "confidence": 0.3149935}, {"type": "TEMPORAL:TIME", "mention": "trente ans", "normalized": "trente ans", "count": 1, "mentionOffsets": [{"startOffset": 8366, "endOffset": 8376}], "entityId": "T51"}, {"type": "TITLE", "mention": "gouverneur", "normalized": "gouverneur", "count": 1, "mentionOffsets": [{"startOffset": 8388, "endOffset": 8398}], "entityId": "T52", "confidence": 0.84538579}, {"type": "IDENTIFIER:DISTANCE", "mention": "quatre pieds", "normalized": "quatre pieds", "count": 1, "mentionOffsets": [{"startOffset": 8793, "endOffset": 8805}], "entityId": "T55"}, {"type": "PERSON", "mention": "Alain", "normalized": "Alain", "count": 1, "mentionOffsets": [{"startOffset": 8902, "endOffset": 8907}], "entityId": "T58", "confidence": 0.47656822}, {"type": "PERSON", "mention": "Mario", "normalized": "Mario", "count": 1, "mentionOffsets": [{"startOffset": 8911, "endOffset": 8916}], "entityId": "T59", "confidence": 0.14364564}, {"type": "PERSON", "mention": "Chouaguen", "normalized": "Chouaguen", "count": 1, "mentionOffsets": [{"startOffset": 9683, "endOffset": 9692}], "entityId": "T68", "confidence": 0.00107861}, {"type": "TEMPORAL:DATE", "mention": "dimanche, 10 septembre 1837", "normalized": "dimanche, 10 septembre 1837", "count": 1, "mentionOffsets": [{"startOffset": 11194, "endOffset": 11221}], "entityId": "T80"}, {"type": "TITLE", "mention": "madame", "normalized": "madame", "count": 1, "mentionOffsets": [{"startOffset": 11478, "endOffset": 11484}], "entityId": "T84", "confidence": 0.3346554}, {"type": "LOCATION", "mention": "Ovide", "normalized": "Ovide", "count": 1, "mentionOffsets": [{"startOffset": 11924, "endOffset": 11929}], "entityId": "T87", "confidence": 0.25762558}, {"type": "TITLE", "mention": "madame", "normalized": "madame", "count": 1, "mentionOffsets": [{"startOffset": 12384, "endOffset": 12390}], "entityId": "T92", "confidence": 0.70564604}, {"type": "TEMPORAL:TIME", "mention": "quarante-deux ans", "normalized": "quarante-deux ans", "count": 1, "mentionOffsets": [{"startOffset": 12497, "endOffset": 12514}], "entityId": "T94"}, {"type": "TITLE", "mention": "madame", "normalized": "madame", "count": 1, "mentionOffsets": [{"startOffset": 12866, "endOffset": 12872}], "entityId": "T96", "confidence": 0.58324015}, {"type": "TEMPORAL:TIME", "mention": "trois ans", "normalized": "trois ans", "count": 1, "mentionOffsets": [{"startOffset": 12981, "endOffset": 12990}], "entityId": "T99"}, {"type": "TITLE", "mention": "Madame", "normalized": "Madame", "count": 1, "mentionOffsets": [{"startOffset": 14201, "endOffset": 14207}], "entityId": "T108", "confidence": 0.81591761}, {"type": "TITLE", "mention": "madame", "normalized": "madame", "count": 1, "mentionOffsets": [{"startOffset": 14374, "endOffset": 14380}], "entityId": "T111", "confidence": 0.30554557}, {"type": "TITLE", "mention": "madame", "normalized": "madame", "count": 1, "mentionOffsets": [{"startOffset": 14728, "endOffset": 14734}], "entityId": "T113", "confidence": 0.80891526}, {"type": "TITLE", "mention": "madame", "normalized": "madame", "count": 1, "mentionOffsets": [{"startOffset": 15037, "endOffset": 15043}], "entityId": "T116", "confidence": 0.30879223}, {"type": "TITLE", "mention": "gouverneur", "normalized": "gouverneur", "count": 1, "mentionOffsets": [{"startOffset": 16490, "endOffset": 16500}], "entityId": "T121", "confidence": 0.91647351}, {"type": "LOCATION", "mention": "Chili", "normalized": "Chili", "count": 1, "mentionOffsets": [{"startOffset": 17151, "endOffset": 17156}], "entityId": "T126", "confidence": 0.44126117}, {"type": "LOCATION", "mention": "Mexique", "normalized": "Mexique", "count": 1, "mentionOffsets": [{"startOffset": 17161, "endOffset": 17168}], "entityId": "T127", "confidence": 0.50254261}, {"type": "LOCATION", "mention": "Br\u00e9sil", "normalized": "Br\u00e9sil", "count": 1, "mentionOffsets": [{"startOffset": 17173, "endOffset": 17179}], "entityId": "T128", "confidence": 0.52614677}, {"type": "LOCATION", "mention": "P\u00e9rou", "normalized": "P\u00e9rou", "count": 1, "mentionOffsets": [{"startOffset": 17184, "endOffset": 17189}], "entityId": "T129", "confidence": 0.37482691}, {"type": "LOCATION", "mention": "Paraguay", "normalized": "Paraguay", "count": 1, "mentionOffsets": [{"startOffset": 17194, "endOffset": 17202}], "entityId": "T130", "confidence": 0.31907797}, {"type": "LOCATION", "mention": "Argentine", "normalized": "Argentine", "count": 1, "mentionOffsets": [{"startOffset": 17207, "endOffset": 17216}], "entityId": "T131", "confidence": 0.66830504}, {"type": "LOCATION", "mention": "Bolivie", "normalized": "Bolivie", "count": 1, "mentionOffsets": [{"startOffset": 17223, "endOffset": 17230}], "entityId": "T132", "confidence": 0.30686867}, {"type": "TEMPORAL:TIME", "mention": "1809 et", "normalized": "1809 et", "count": 1, "mentionOffsets": [{"startOffset": 17248, "endOffset": 17255}], "entityId": "T133"}, {"type": "LOCATION", "mention": "Gr\u00e8ce", "normalized": "Gr\u00e8ce", "count": 1, "mentionOffsets": [{"startOffset": 17288, "endOffset": 17293}], "entityId": "T134", "confidence": 0.72798848}, {"type": "LOCATION", "mention": "Belgique", "normalized": "Belgique", "count": 1, "mentionOffsets": [{"startOffset": 17309, "endOffset": 17317}], "entityId": "T135", "confidence": 0.65490663}, {"type": "TEMPORAL:TIME", "mention": "1830 et", "normalized": "1830 et", "count": 1, "mentionOffsets": [{"startOffset": 17321, "endOffset": 17328}], "entityId": "T136"}, {"type": "TEMPORAL:DATE", "mention": "Juillet", "normalized": "Juillet", "count": 1, "mentionOffsets": [{"startOffset": 17349, "endOffset": 17356}], "entityId": "T137"}, {"type": "LOCATION", "mention": "France", "normalized": "France", "count": 1, "mentionOffsets": [{"startOffset": 17377, "endOffset": 17383}], "entityId": "T138", "confidence": 0.83385861}, {"type": "TITLE", "mention": "commandant", "normalized": "commandant", "count": 1, "mentionOffsets": [{"startOffset": 18072, "endOffset": 18082}], "entityId": "T140", "confidence": 0.504035}, {"type": "PERSON", "mention": "Colborne", "normalized": "Colborne", "count": 1, "mentionOffsets": [{"startOffset": 18083, "endOffset": 18091}], "entityId": "T141", "confidence": 0.9036358}, {"type": "TITLE", "mention": "madame", "normalized": "madame", "count": 1, "mentionOffsets": [{"startOffset": 18708, "endOffset": 18714}], "entityId": "T145", "confidence": 0.58623064}, {"type": "LOCATION", "mention": "Saint-Charles", "normalized": "Saint-Charles", "count": 1, "mentionOffsets": [{"startOffset": 18966, "endOffset": 18979}], "entityId": "T148", "confidence": 0.67590344}, {"type": "TITLE", "mention": "madame", "normalized": "madame", "count": 1, "mentionOffsets": [{"startOffset": 19863, "endOffset": 19869}], "entityId": "T154", "confidence": 0.72455192}, {"type": "PERSON", "mention": "Charles Pellerin", "normalized": "Charles Pellerin", "count": 1, "mentionOffsets": [{"startOffset": 20029, "endOffset": 20045}], "entityId": "T160", "confidence": 0.1606288}, {"type": "TITLE", "mention": "mademoiselle", "normalized": "mademoiselle", "count": 1, "mentionOffsets": [{"startOffset": 20780, "endOffset": 20792}], "entityId": "T167", "confidence": 0.10092306}, {"type": "LOCATION", "mention": "Londres", "normalized": "Londres", "count": 1, "mentionOffsets": [{"startOffset": 21090, "endOffset": 21097}], "entityId": "T171", "confidence": 0.6756779}, {"type": "LOCATION", "mention": "Plymouth", "normalized": "Plymouth", "count": 1, "mentionOffsets": [{"startOffset": 21178, "endOffset": 21186}], "entityId": "T172", "confidence": 0.54740202}, {"type": "PERSON", "mention": "Elise", "normalized": "Elise", "count": 1, "mentionOffsets": [{"startOffset": 21868, "endOffset": 21873}], "entityId": "T175", "confidence": 0.18863428}, {"type": "ORGANIZATION", "mention": "Beethoven", "normalized": "Beethoven", "count": 1, "mentionOffsets": [{"startOffset": 21889, "endOffset": 21898}], "entityId": "T176", "confidence": 0.19201517}, {"type": "TEMPORAL:DATE", "mention": "samedi, 16 septembre 1837", "normalized": "samedi, 16 septembre 1837", "count": 1, "mentionOffsets": [{"startOffset": 21995, "endOffset": 22020}], "entityId": "T179"}, {"type": "PERSON", "mention": "Raymond Cusson", "normalized": "Raymond Cusson", "count": 1, "mentionOffsets": [{"startOffset": 22022, "endOffset": 22036}], "entityId": "T180", "confidence": 0.91493666}, {"type": "PERSON", "mention": "G\u00e9d\u00e9on", "normalized": "G\u00e9d\u00e9on", "count": 1, "mentionOffsets": [{"startOffset": 22891, "endOffset": 22897}], "entityId": "T182", "confidence": 0.22146952}, {"type": "LOCATION", "mention": "Saint-Joseph-de-Chambly", "normalized": "Saint-Joseph-de-Chambly", "count": 1, "mentionOffsets": [{"startOffset": 24556, "endOffset": 24579}], "entityId": "T196", "confidence": 0.57662559}, {"type": "TEMPORAL:DATE", "mention": "ao\u00fbt 1835", "normalized": "ao\u00fbt 1835", "count": 1, "mentionOffsets": [{"startOffset": 24922, "endOffset": 24931}], "entityId": "T199"}, {"type": "TITLE", "mention": "monsieur", "normalized": "monsieur", "count": 1, "mentionOffsets": [{"startOffset": 27360, "endOffset": 27368}], "entityId": "T217", "confidence": 0.04623079}, {"type": "PERSON", "mention": "Marie", "normalized": "Marie", "count": 1, "mentionOffsets": [{"startOffset": 27647, "endOffset": 27652}], "entityId": "T219", "confidence": 0.36317623}, {"type": "TEMPORAL:DATE", "mention": "mai", "normalized": "mai", "count": 1, "mentionOffsets": [{"startOffset": 28082, "endOffset": 28085}], "entityId": "T222"}, {"type": "PERSON", "mention": "Sophie", "normalized": "Sophie", "count": 1, "mentionOffsets": [{"startOffset": 28496, "endOffset": 28502}], "entityId": "T223", "confidence": 0.19123554}, {"type": "ORGANIZATION", "mention": "Minerve", "normalized": "Minerve", "count": 1, "mentionOffsets": [{"startOffset": 29019, "endOffset": 29026}], "entityId": "T226", "confidence": 0.33892739}, {"type": "TEMPORAL:DATE", "mention": "dimanche", "normalized": "dimanche", "count": 1, "mentionOffsets": [{"startOffset": 31048, "endOffset": 31056}], "entityId": "T243"}, {"type": "LOCATION", "mention": "rivi\u00e8re Chambly", "normalized": "rivi\u00e8re Chambly", "count": 1, "mentionOffsets": [{"startOffset": 31133, "endOffset": 31148}], "entityId": "T244", "confidence": 0.01973307}, {"type": "TEMPORAL:DATE", "mention": "dimanche, 17 septembre 1837", "normalized": "dimanche, 17 septembre 1837", "count": 1, "mentionOffsets": [{"startOffset": 33227, "endOffset": 33254}], "entityId": "T258"}, {"type": "TEMPORAL:DATE", "mention": "septembre", "normalized": "septembre", "count": 1, "mentionOffsets": [{"startOffset": 33338, "endOffset": 33347}], "entityId": "T261"}, {"type": "PERSON", "mention": "Russell", "normalized": "Russell", "count": 1, "mentionOffsets": [{"startOffset": 36523, "endOffset": 36530}], "entityId": "T275", "confidence": 0.36832309}, {"type": "TITLE", "mention": "gouverneur", "normalized": "gouverneur", "count": 1, "mentionOffsets": [{"startOffset": 36881, "endOffset": 36891}], "entityId": "T277", "confidence": 0.69862521}, {"type": "LOCATION", "mention": "Saint-Jean", "normalized": "Saint-Jean", "count": 1, "mentionOffsets": [{"startOffset": 37950, "endOffset": 37960}], "entityId": "T279", "confidence": 0.55472672}], "responseHeaders": {"Content-Encoding": "gzip", "Content-Type": "application/json", "Date": "Fri, 07 Dec 2018 12:21:41 GMT", "Server": "openresty", "Strict-Transport-Security": "max-age=63072000; includeSubDomains; preload", "Vary": "Accept-Encoding", "X-RosetteAPI-App-Id": "1409618042655", "X-RosetteAPI-Concurrency": "2", "X-RosetteAPI-ProcessedLanguage": "fra", "X-RosetteAPI-Request-Id": "89a78f3b3b169a49de5bca4a0c45ec97", "Content-Length": "4491", "Connection": "keep-alive"}}